rcli/__init__.py
rcli/autodetect.py
rcli/call.py
rcli/config.py
rcli/dispatcher.py
rcli/exceptions.py
rcli/log.py
rcli/usage.py
rcli/backports/__init__.py
rcli/backports/get_terminal_size.py
rcli/display/__init__.py
rcli/display/box.py
rcli/display/io.py
rcli/display/style.py
rcli/display/terminal.py
rcli/display/util.py
rcli-0.5.2.dist-info/LICENSE
rcli-0.5.2.dist-info/METADATA
rcli-0.5.2.dist-info/WHEEL
rcli-0.5.2.dist-info/entry_points.txt
rcli-0.5.2.dist-info/top_level.txt
rcli-0.5.2.dist-info/RECORD
