Metadata-Version: 2.1
Name: rcli
Version: 0.5.2
Summary: A library for rapidly creating command-line tools.
Home-page: https://github.com/contains-io/rcli
Author: Melissa Nuno
Author-email: melissa@contains.io
License: MIT
Keywords: docopt,commands,subcommands,tooling,cli
Platform: UNKNOWN
Classifier: Development Status :: 3 - Alpha
Classifier: License :: OSI Approved :: MIT License
Classifier: Operating System :: OS Independent
Classifier: Programming Language :: Python
Classifier: Programming Language :: Python :: 3
Classifier: Programming Language :: Python :: 3.6
Classifier: Programming Language :: Python :: 3.7
Classifier: Programming Language :: Python :: 3.8
Classifier: Intended Audience :: Developers
Classifier: Topic :: Utilities
Requires-Dist: typet (<0.5,>=0.4)
Requires-Dist: backports.shutil-get-terminal-size
Requires-Dist: colorama (<1,>=0.3.6)
Requires-Dist: tqdm (<5,>=4.9.0)
Requires-Dist: docopt (<1,>=0.6.2)
Requires-Dist: six (>=1.10.0)
